django_sample_generator/__init__.py
django_sample_generator/__main__.py
django_sample_generator/constants.py
django_sample_generator/fields.py
django_sample_generator/functions.py
django_sample_generator/generator.py
django_sample_generator/mock.png
django_sample_generator/mock.txt
django_sample_generator/register.py
django_sample_generator/text_db
django_sample_generator/text_generator.py
django_sample_generator/management/__init__.py
django_sample_generator/management/commands/__init__.py
django_sample_generator/management/commands/create_sample_data.py
django_sample_data_generator-1.0.5.dist-info/AUTHORS
django_sample_data_generator-1.0.5.dist-info/LICENSE
django_sample_data_generator-1.0.5.dist-info/METADATA
django_sample_data_generator-1.0.5.dist-info/WHEEL
django_sample_data_generator-1.0.5.dist-info/top_level.txt
django_sample_data_generator-1.0.5.dist-info/RECORD
