Metadata-Version: 2.1
Name: django-sample-data-generator
Version: 1.0.5
Summary: Sample data generator
Author-email: Miroslav Bendík <miroslav.bendik@gmail.com>
License: MIT
Project-URL: homepage, https://github.com/mireq/django-django-sample-data-generator
Project-URL: documentation, https://github.com/mireq/django-django-sample-data-generator
Project-URL: repository, https://github.com/mireq/django-django-sample-data-generator
Project-URL: changelog, https://github.com/mireq/django-django-sample-data-generator/blob/master/CHANGELOG.md
Keywords: django,sample data
Classifier: Programming Language :: Python :: 3
Requires-Python: >=3.7
License-File: LICENSE
License-File: AUTHORS
Requires-Dist: django
Provides-Extra: dev
Requires-Dist: tox ; extra == 'dev'
Requires-Dist: pylint ; extra == 'dev'
Requires-Dist: pre-commit ; extra == 'dev'
Requires-Dist: bump2version ; extra == 'dev'
Requires-Dist: commitizen ; extra == 'dev'
